{
 "files": [
  {
   "name": ".",
   "ftype": "dir",
   "chksum_type": null,
   "chksum_sha256": null,
   "format": 1
  },
  {
   "name": "LICENSE",
   "ftype": "file",
   "chksum_type": "sha256",
   "chksum_sha256": "39a8efc0145a559cd2223afc7339bf4225418e70016e3e9e8fab157fdd52422a",
   "format": 1
  },
  {
   "name": "Pipfile",
   "ftype": "file",
   "chksum_type": "sha256",
   "chksum_sha256": "647e7e67cd4a98dd0db67653ac2e5f76691f97a43600564f64a62607d9916e06",
   "format": 1
  },
  {
   "name": "docs",
   "ftype": "dir",
   "chksum_type": null,
   "chksum_sha256": null,
   "format": 1
  },
  {
   "name": "docs/002-topology.md",
   "ftype": "file",
   "chksum_type": "sha256",
   "chksum_sha256": "5722cb7f9ae7611851f14cc3321cf4cddaba677d926a98eb9ed416b9134fcc58",
   "format": 1
  },
  {
   "name": "docs/001-metadata.md",
   "ftype": "file",
   "chksum_type": "sha256",
   "chksum_sha256": "dafc4e8e9c3f3365e4ec4c4e36eaac1d4ec3a53de5c6c62a0bfbc0fa38eeaa02",
   "format": 1
  },
  {
   "name": "docs/000-template.md",
   "ftype": "file",
   "chksum_type": "sha256",
   "chksum_sha256": "033efc0ab84555ee83429714f2a2b175dbc20388a0d1262b06370280a42c3864",
   "format": 1
  },
  {
   "name": "playbooks",
   "ftype": "dir",
   "chksum_type": null,
   "chksum_sha256": null,
   "format": 1
  },
  {
   "name": "playbooks/standard-debian.yml",
   "ftype": "file",
   "chksum_type": "sha256",
   "chksum_sha256": "22caa633ca95bb095cedd1295e4d94417f0645dc2406ee3c849798b31e97bc93",
   "format": 1
  },
  {
   "name": "playbooks/standard-tailscale.yml",
   "ftype": "file",
   "chksum_type": "sha256",
   "chksum_sha256": "4da0e1fc10a7f1139fdcbe1f8ef56e1c53ddfede55f50c4dcc8c66c24ff55b88",
   "format": 1
  },
  {
   "name": "playbooks/standard-ssh.yml",
   "ftype": "file",
   "chksum_type": "sha256",
   "chksum_sha256": "c9906b8bd8da01499e7d73a8ff5dc10b57fa4c33450ded1ccfa27edb392a0976",
   "format": 1
  },
  {
   "name": "playbooks/standard-kubernetes.yml",
   "ftype": "file",
   "chksum_type": "sha256",
   "chksum_sha256": "05d83a9c5a6bf64912d9d80560756d39703ef1d6eb160a11269655565708ac18",
   "format": 1
  },
  {
   "name": "roles",
   "ftype": "dir",
   "chksum_type": null,
   "chksum_sha256": null,
   "format": 1
  },
  {
   "name": "roles/tailscale",
   "ftype": "dir",
   "chksum_type": null,
   "chksum_sha256": null,
   "format": 1
  },
  {
   "name": "roles/tailscale/tasks",
   "ftype": "dir",
   "chksum_type": null,
   "chksum_sha256": null,
   "format": 1
  },
  {
   "name": "roles/tailscale/tasks/200-configuration.yml",
   "ftype": "file",
   "chksum_type": "sha256",
   "chksum_sha256": "8174264d96c0aa6fe3877c21238bf11f6a48debf7d43e2b1f401aa1b1a3460ee",
   "format": 1
  },
  {
   "name": "roles/tailscale/tasks/100-install.yml",
   "ftype": "file",
   "chksum_type": "sha256",
   "chksum_sha256": "38ad155ebf32ead6deda4b7725439ae16d64d55c964553cfd674cfc3298cd942",
   "format": 1
  },
  {
   "name": "roles/tailscale/tasks/300-metadata.yml",
   "ftype": "file",
   "chksum_type": "sha256",
   "chksum_sha256": "b6b48a533fc68309b9a69281402d214d84ca9c439b2389acf98ed2d7f7e711a3",
   "format": 1
  },
  {
   "name": "roles/tailscale/tasks/000-prerequisite.yml",
   "ftype": "file",
   "chksum_type": "sha256",
   "chksum_sha256": "89da2d522786832c42321718c70455357de74dbe12bc21b68d14f4da1fd80682",
   "format": 1
  },
  {
   "name": "roles/tailscale/tasks/main.yml",
   "ftype": "file",
   "chksum_type": "sha256",
   "chksum_sha256": "caacd92ff0694ddff9d12f18c7e46f9f13ae2b0c25173a2114a0a392f4fa6d57",
   "format": 1
  },
  {
   "name": "roles/tailscale/defaults",
   "ftype": "dir",
   "chksum_type": null,
   "chksum_sha256": null,
   "format": 1
  },
  {
   "name": "roles/tailscale/defaults/main.yml",
   "ftype": "file",
   "chksum_type": "sha256",
   "chksum_sha256": "1de804cc9db4bdfcd8e13cdc50232cd5287255608e348a1531dc8fefe86a0ed6",
   "format": 1
  },
  {
   "name": "roles/tailscale/handlers",
   "ftype": "dir",
   "chksum_type": null,
   "chksum_sha256": null,
   "format": 1
  },
  {
   "name": "roles/tailscale/handlers/main.yml",
   "ftype": "file",
   "chksum_type": "sha256",
   "chksum_sha256": "e56e77cf0ee8755ca1f5007b6f190f82b937ecbf7d155b85c049c9df52fc52d9",
   "format": 1
  },
  {
   "name": "roles/tailscale/vars",
   "ftype": "dir",
   "chksum_type": null,
   "chksum_sha256": null,
   "format": 1
  },
  {
   "name": "roles/tailscale/vars/main.yml",
   "ftype": "file",
   "chksum_type": "sha256",
   "chksum_sha256": "342649fafc87569a359846ac1e4f6fb2c3baf3ea1f1e2d70f1ee1890b210836d",
   "format": 1
  },
  {
   "name": "roles/tailscale/templates",
   "ftype": "dir",
   "chksum_type": null,
   "chksum_sha256": null,
   "format": 1
  },
  {
   "name": "roles/tailscale/templates/.gitkeep",
   "ftype": "file",
   "chksum_type": "sha256",
   "chksum_sha256": "e3b0c44298fc1c149afbf4c8996fb92427ae41e4649b934ca495991b7852b855",
   "format": 1
  },
  {
   "name": "roles/tailscale/files",
   "ftype": "dir",
   "chksum_type": null,
   "chksum_sha256": null,
   "format": 1
  },
  {
   "name": "roles/tailscale/files/.gitkeep",
   "ftype": "file",
   "chksum_type": "sha256",
   "chksum_sha256": "e3b0c44298fc1c149afbf4c8996fb92427ae41e4649b934ca495991b7852b855",
   "format": 1
  },
  {
   "name": "roles/tailscale/meta",
   "ftype": "dir",
   "chksum_type": null,
   "chksum_sha256": null,
   "format": 1
  },
  {
   "name": "roles/tailscale/meta/main.yml",
   "ftype": "file",
   "chksum_type": "sha256",
   "chksum_sha256": "0c12b2ee75d06b4e6160203c0bd2a7601e6bc359f02d790d82442c9225943ab1",
   "format": 1
  },
  {
   "name": "roles/tailscale/README.md",
   "ftype": "file",
   "chksum_type": "sha256",
   "chksum_sha256": "fb578d5d2991e068d0afc95b5baddf07a0d16835c513661f91454f59ed69b872",
   "format": 1
  },
  {
   "name": "roles/metadata",
   "ftype": "dir",
   "chksum_type": null,
   "chksum_sha256": null,
   "format": 1
  },
  {
   "name": "roles/metadata/tasks",
   "ftype": "dir",
   "chksum_type": null,
   "chksum_sha256": null,
   "format": 1
  },
  {
   "name": "roles/metadata/tasks/000-prerequisites.yml",
   "ftype": "file",
   "chksum_type": "sha256",
   "chksum_sha256": "d08965cbb80e6feae0cae35d0d7e0e1bf952da13670bc62738a6236d5f24ff17",
   "format": 1
  },
  {
   "name": "roles/metadata/tasks/100-topology.yml",
   "ftype": "file",
   "chksum_type": "sha256",
   "chksum_sha256": "fbbcb1268b366aa0e28d4979cd0e89cc69ead3a3723ece5e1d6c41a40486c0c1",
   "format": 1
  },
  {
   "name": "roles/metadata/tasks/main.yml",
   "ftype": "file",
   "chksum_type": "sha256",
   "chksum_sha256": "6570eee2da25a140eb63536c5801efc86eb7a14f6e39cf36da9c33734a53ccb8",
   "format": 1
  },
  {
   "name": "roles/metadata/defaults",
   "ftype": "dir",
   "chksum_type": null,
   "chksum_sha256": null,
   "format": 1
  },
  {
   "name": "roles/metadata/defaults/main.yml",
   "ftype": "file",
   "chksum_type": "sha256",
   "chksum_sha256": "f26297b971d88faf1427229400943effacb8049d437122a1bd8f73b2acdc6baf",
   "format": 1
  },
  {
   "name": "roles/metadata/vars",
   "ftype": "dir",
   "chksum_type": null,
   "chksum_sha256": null,
   "format": 1
  },
  {
   "name": "roles/metadata/vars/main.yml",
   "ftype": "file",
   "chksum_type": "sha256",
   "chksum_sha256": "a1929ccbd78ede03491ee0008c61bc727b38eb8adb2cecc6a64a46655d5ab198",
   "format": 1
  },
  {
   "name": "roles/kubernetes",
   "ftype": "dir",
   "chksum_type": null,
   "chksum_sha256": null,
   "format": 1
  },
  {
   "name": "roles/kubernetes/tasks",
   "ftype": "dir",
   "chksum_type": null,
   "chksum_sha256": null,
   "format": 1
  },
  {
   "name": "roles/kubernetes/tasks/120-kubectl.yml",
   "ftype": "file",
   "chksum_type": "sha256",
   "chksum_sha256": "46f4ca6319a6ee785f2f22088a348ede0f5f7c508a1d6a3714453c43065a158a",
   "format": 1
  },
  {
   "name": "roles/kubernetes/tasks/100-kubeadm.yml",
   "ftype": "file",
   "chksum_type": "sha256",
   "chksum_sha256": "c2237b6fdf28bdb1ee63b4005b264518fb7a62bb84f1d7bed7a0dce88da69930",
   "format": 1
  },
  {
   "name": "roles/kubernetes/tasks/000-prerequisites.yml",
   "ftype": "file",
   "chksum_type": "sha256",
   "chksum_sha256": "810048d6fa5c9db75f5ce80b2bcf5b041c1b6243e0990c98b7fd0ac385b23183",
   "format": 1
  },
  {
   "name": "roles/kubernetes/tasks/110-kubelet.yml",
   "ftype": "file",
   "chksum_type": "sha256",
   "chksum_sha256": "7f40d5a1bf0e43130783a41c040bb45c12139213f2cfd57231600b01d8d83fa7",
   "format": 1
  },
  {
   "name": "roles/kubernetes/tasks/main.yml",
   "ftype": "file",
   "chksum_type": "sha256",
   "chksum_sha256": "bee2db015c50b767fbaf6020d8995656c11205c956879d0c79d642c1d81782f0",
   "format": 1
  },
  {
   "name": "roles/kubernetes/tasks/010-containerd.yml",
   "ftype": "file",
   "chksum_type": "sha256",
   "chksum_sha256": "9035cf8e04d2c8a46319a7388863b4e55f45b212459d198cf5b2a871d1b446fc",
   "format": 1
  },
  {
   "name": "roles/kubernetes/tasks/020-packages.yml",
   "ftype": "file",
   "chksum_type": "sha256",
   "chksum_sha256": "0e1d0f3beff32072a2b06011e266e7e76476dc428f2328f13ee2e3a3a80d53ca",
   "format": 1
  },
  {
   "name": "roles/kubernetes/defaults",
   "ftype": "dir",
   "chksum_type": null,
   "chksum_sha256": null,
   "format": 1
  },
  {
   "name": "roles/kubernetes/defaults/main.yml",
   "ftype": "file",
   "chksum_type": "sha256",
   "chksum_sha256": "ccee099b345cc363c3084e8dfe26aaf3d2c1a7653327cac2033793964cb769ab",
   "format": 1
  },
  {
   "name": "roles/kubernetes/vars",
   "ftype": "dir",
   "chksum_type": null,
   "chksum_sha256": null,
   "format": 1
  },
  {
   "name": "roles/kubernetes/vars/main.yml",
   "ftype": "file",
   "chksum_type": "sha256",
   "chksum_sha256": "55c80c9fdbbf87bf495e07a3e5d2380f29aa7dc0f110846ffbe649e9e96c970a",
   "format": 1
  },
  {
   "name": "roles/linux",
   "ftype": "dir",
   "chksum_type": null,
   "chksum_sha256": null,
   "format": 1
  },
  {
   "name": "roles/linux/apt",
   "ftype": "dir",
   "chksum_type": null,
   "chksum_sha256": null,
   "format": 1
  },
  {
   "name": "roles/linux/apt/tasks",
   "ftype": "dir",
   "chksum_type": null,
   "chksum_sha256": null,
   "format": 1
  },
  {
   "name": "roles/linux/apt/tasks/main.yml",
   "ftype": "file",
   "chksum_type": "sha256",
   "chksum_sha256": "82cf2ce5d77e23e845ccb96d6d0fc51ef1db532370c91c8e79722220ec29a671",
   "format": 1
  },
  {
   "name": "roles/linux/apt/files",
   "ftype": "dir",
   "chksum_type": null,
   "chksum_sha256": null,
   "format": 1
  },
  {
   "name": "roles/linux/apt/files/sources.list",
   "ftype": "file",
   "chksum_type": "sha256",
   "chksum_sha256": "7c816c7364e58c528b18d5f56e6f7cc965e484e058a76b6312b8fc3f88f191c1",
   "format": 1
  },
  {
   "name": "roles/linux/debian",
   "ftype": "dir",
   "chksum_type": null,
   "chksum_sha256": null,
   "format": 1
  },
  {
   "name": "roles/linux/debian/.yamllint",
   "ftype": "file",
   "chksum_type": "sha256",
   "chksum_sha256": "6c497da0587491d2a4eb22aa89007e45ddb4dfe1049cc3a347e65c77a833316a",
   "format": 1
  },
  {
   "name": "roles/linux/debian/.gitignore",
   "ftype": "file",
   "chksum_type": "sha256",
   "chksum_sha256": "6f6e2a11c8c063df61e593cdb78096cff8252b921c4800dda949a46bf16bd8e0",
   "format": 1
  },
  {
   "name": "roles/linux/debian/tasks",
   "ftype": "dir",
   "chksum_type": null,
   "chksum_sha256": null,
   "format": 1
  },
  {
   "name": "roles/linux/debian/tasks/300-pre-configure.yml",
   "ftype": "file",
   "chksum_type": "sha256",
   "chksum_sha256": "97750738442484d2bd0bd56c0d62abc1ae2e0002f73b67558f1c73ca9ff07a38",
   "format": 1
  },
  {
   "name": "roles/linux/debian/tasks/999-metadata.yml",
   "ftype": "file",
   "chksum_type": "sha256",
   "chksum_sha256": "836b4c8a1bf3e47231c0559a840ed93c63720b00e3d27033a104edbaf3eb4ffe",
   "format": 1
  },
  {
   "name": "roles/linux/debian/tasks/400-auto-uninstall.yml",
   "ftype": "file",
   "chksum_type": "sha256",
   "chksum_sha256": "42d31943405d887da0e0a49d76588141930b56d2d2aaf77aa5800888a5ca45f8",
   "format": 1
  },
  {
   "name": "roles/linux/debian/tasks/310-pre-configure-kernel.yml",
   "ftype": "file",
   "chksum_type": "sha256",
   "chksum_sha256": "060dc5fcc997d4e7be578f84c4202d9b48f09010205f212aced1341a0704c6e4",
   "format": 1
  },
  {
   "name": "roles/linux/debian/tasks/000-prerequisites.yml",
   "ftype": "file",
   "chksum_type": "sha256",
   "chksum_sha256": "a91f913863a7050325c70979cc07f9aa0e2106cdc3a31fea9d100d1ef7e937d0",
   "format": 1
  },
  {
   "name": "roles/linux/debian/tasks/320-pre-configure-swap.yml",
   "ftype": "file",
   "chksum_type": "sha256",
   "chksum_sha256": "0ac04d77114993cbbbb065bfff2b704813ea160ed331e77d32e3dd2195a371e3",
   "format": 1
  },
  {
   "name": "roles/linux/debian/tasks/main.yml",
   "ftype": "file",
   "chksum_type": "sha256",
   "chksum_sha256": "d2e325912f17a4d6809413f5a94a46dc34e28df6f95ad6ace35e7546e78ff36f",
   "format": 1
  },
  {
   "name": "roles/linux/debian/tasks/200-auto-install.yml",
   "ftype": "file",
   "chksum_type": "sha256",
   "chksum_sha256": "02ed5f173cef07075481e10d7a4163626f1b5aa43bdca71865ff8ebdcf7bff9d",
   "format": 1
  },
  {
   "name": "roles/linux/debian/tasks/500-post-configuration.yml",
   "ftype": "file",
   "chksum_type": "sha256",
   "chksum_sha256": "77a3d19fd484f49cdbe11a5b128d906860dfba4ffb0d9da83677e238c99068c6",
   "format": 1
  },
  {
   "name": "roles/linux/debian/defaults",
   "ftype": "dir",
   "chksum_type": null,
   "chksum_sha256": null,
   "format": 1
  },
  {
   "name": "roles/linux/debian/defaults/main.yml",
   "ftype": "file",
   "chksum_type": "sha256",
   "chksum_sha256": "6356dd79c8725907d833e39f73711ddda073989962cb02494c881d6fbebba177",
   "format": 1
  },
  {
   "name": "roles/linux/debian/handlers",
   "ftype": "dir",
   "chksum_type": null,
   "chksum_sha256": null,
   "format": 1
  },
  {
   "name": "roles/linux/debian/handlers/main.yml",
   "ftype": "file",
   "chksum_type": "sha256",
   "chksum_sha256": "e3705c3905c85ca93254396fa7d3a683d280739465099ae948135e7d1aa560ba",
   "format": 1
  },
  {
   "name": "roles/linux/debian/vars",
   "ftype": "dir",
   "chksum_type": null,
   "chksum_sha256": null,
   "format": 1
  },
  {
   "name": "roles/linux/debian/vars/main.yml",
   "ftype": "file",
   "chksum_type": "sha256",
   "chksum_sha256": "426d4b8920407b75b75b740a6bc8cfc7e3dee6e98a205eb3db44519256f14ee8",
   "format": 1
  },
  {
   "name": "roles/linux/debian/templates",
   "ftype": "dir",
   "chksum_type": null,
   "chksum_sha256": null,
   "format": 1
  },
  {
   "name": "roles/linux/debian/templates/motd.txt.j2",
   "ftype": "file",
   "chksum_type": "sha256",
   "chksum_sha256": "679a8114b5350e14d9f7caaf8fd777b1c5e22afc75dd480aa61a172047e7bb66",
   "format": 1
  },
  {
   "name": "roles/linux/debian/meta",
   "ftype": "dir",
   "chksum_type": null,
   "chksum_sha256": null,
   "format": 1
  },
  {
   "name": "roles/linux/debian/meta/main.yml",
   "ftype": "file",
   "chksum_type": "sha256",
   "chksum_sha256": "7814f6aea65295a469f92c1e1f6e374774b8bb3dc8bf34b812e42731b0185752",
   "format": 1
  },
  {
   "name": "roles/linux/debian/README.md",
   "ftype": "file",
   "chksum_type": "sha256",
   "chksum_sha256": "733e765eb6f0a17334339998194dc46670dd82b1e88277855b432961ad877b70",
   "format": 1
  },
  {
   "name": "roles/ssh",
   "ftype": "dir",
   "chksum_type": null,
   "chksum_sha256": null,
   "format": 1
  },
  {
   "name": "roles/ssh/tasks",
   "ftype": "dir",
   "chksum_type": null,
   "chksum_sha256": null,
   "format": 1
  },
  {
   "name": "roles/ssh/tasks/100-install.yml",
   "ftype": "file",
   "chksum_type": "sha256",
   "chksum_sha256": "94a5fcfc1537ce7035f92e0b3ceb7f52e3cf658423b479bd4230f357d101c887",
   "format": 1
  },
  {
   "name": "roles/ssh/tasks/200-hardening.yml",
   "ftype": "file",
   "chksum_type": "sha256",
   "chksum_sha256": "ebca78b2e4677ad7cfd8575ef88feea724dca7dbb661ddcb35d247ed5298e46e",
   "format": 1
  },
  {
   "name": "roles/ssh/tasks/000-prerequisites.yml",
   "ftype": "file",
   "chksum_type": "sha256",
   "chksum_sha256": "e3b0c44298fc1c149afbf4c8996fb92427ae41e4649b934ca495991b7852b855",
   "format": 1
  },
  {
   "name": "roles/ssh/tasks/300-access-control.yml",
   "ftype": "file",
   "chksum_type": "sha256",
   "chksum_sha256": "c2d18aff05e829c9a5dbd4651bb75d84158d7c8bfcf4f354f75d6c098fdcd7b8",
   "format": 1
  },
  {
   "name": "roles/ssh/tasks/main.yml",
   "ftype": "file",
   "chksum_type": "sha256",
   "chksum_sha256": "4fd678d94fc23f8e0cc5e7e4964e72cb4348bb12f6730ed672d8853163a423b5",
   "format": 1
  },
  {
   "name": "roles/ssh/defaults",
   "ftype": "dir",
   "chksum_type": null,
   "chksum_sha256": null,
   "format": 1
  },
  {
   "name": "roles/ssh/defaults/main.yml",
   "ftype": "file",
   "chksum_type": "sha256",
   "chksum_sha256": "8cb2177fdf9c874c3ee3c1c65b2a11237c43ad8a4272e8685637f34c17cf7af2",
   "format": 1
  },
  {
   "name": "roles/ssh/handlers",
   "ftype": "dir",
   "chksum_type": null,
   "chksum_sha256": null,
   "format": 1
  },
  {
   "name": "roles/ssh/handlers/main.yml",
   "ftype": "file",
   "chksum_type": "sha256",
   "chksum_sha256": "06a2a99d6fc9b5807f031325113896afc5dadf44e0b5d5b6c3ddf5b8123ef4c4",
   "format": 1
  },
  {
   "name": "roles/ssh/vars",
   "ftype": "dir",
   "chksum_type": null,
   "chksum_sha256": null,
   "format": 1
  },
  {
   "name": "roles/ssh/vars/main.yml",
   "ftype": "file",
   "chksum_type": "sha256",
   "chksum_sha256": "f52d711103d50a437830c6fbcd04fb4bab49a0f82f6d26d1c791c6e8488dd090",
   "format": 1
  },
  {
   "name": "roles/ssh/templates",
   "ftype": "dir",
   "chksum_type": null,
   "chksum_sha256": null,
   "format": 1
  },
  {
   "name": "roles/ssh/templates/.gitkeep",
   "ftype": "file",
   "chksum_type": "sha256",
   "chksum_sha256": "e3b0c44298fc1c149afbf4c8996fb92427ae41e4649b934ca495991b7852b855",
   "format": 1
  },
  {
   "name": "roles/ssh/files",
   "ftype": "dir",
   "chksum_type": null,
   "chksum_sha256": null,
   "format": 1
  },
  {
   "name": "roles/ssh/files/.gitkeep",
   "ftype": "file",
   "chksum_type": "sha256",
   "chksum_sha256": "e3b0c44298fc1c149afbf4c8996fb92427ae41e4649b934ca495991b7852b855",
   "format": 1
  },
  {
   "name": "roles/ssh/meta",
   "ftype": "dir",
   "chksum_type": null,
   "chksum_sha256": null,
   "format": 1
  },
  {
   "name": "roles/ssh/meta/main.yml",
   "ftype": "file",
   "chksum_type": "sha256",
   "chksum_sha256": "75c1e732fd5324ff68fae761fb712689cfc38ad2cfbdb06794e916207e3bc9c6",
   "format": 1
  },
  {
   "name": "roles/ssh/README.md",
   "ftype": "file",
   "chksum_type": "sha256",
   "chksum_sha256": "348d95de876d0258a5a7890ae5a0be536483b7181c8aac5154758ab1eda21ffd",
   "format": 1
  },
  {
   "name": "meta",
   "ftype": "dir",
   "chksum_type": null,
   "chksum_sha256": null,
   "format": 1
  },
  {
   "name": "meta/runtime.yml",
   "ftype": "file",
   "chksum_type": "sha256",
   "chksum_sha256": "23b2e0ac15f343e7ce77987d72a6460b73a0bbcd96c22fb8c6161aa2fe0fefee",
   "format": 1
  },
  {
   "name": "CHANGELOG.md",
   "ftype": "file",
   "chksum_type": "sha256",
   "chksum_sha256": "9e280fce9bb62828c9d6c172716cdf01def94f0a85be7fd40797b4616e5f33e4",
   "format": 1
  },
  {
   "name": "README.md",
   "ftype": "file",
   "chksum_type": "sha256",
   "chksum_sha256": "b7bc9da9ba357269fab277e25b557393d93055a628b30ec1deb05ed113706463",
   "format": 1
  },
  {
   "name": ".ansible",
   "ftype": "dir",
   "chksum_type": null,
   "chksum_sha256": null,
   "format": 1
  },
  {
   "name": ".ansible/.lock",
   "ftype": "file",
   "chksum_type": "sha256",
   "chksum_sha256": "e3b0c44298fc1c149afbf4c8996fb92427ae41e4649b934ca495991b7852b855",
   "format": 1
  },
  {
   "name": ".ansible/modules",
   "ftype": "dir",
   "chksum_type": null,
   "chksum_sha256": null,
   "format": 1
  },
  {
   "name": ".ansible/roles",
   "ftype": "dir",
   "chksum_type": null,
   "chksum_sha256": null,
   "format": 1
  },
  {
   "name": ".ansible/collections",
   "ftype": "dir",
   "chksum_type": null,
   "chksum_sha256": null,
   "format": 1
  },
  {
   "name": ".ansible/collections/ansible_collections",
   "ftype": "dir",
   "chksum_type": null,
   "chksum_sha256": null,
   "format": 1
  },
  {
   "name": ".ansible/collections/ansible_collections/adaptivegears",
   "ftype": "dir",
   "chksum_type": null,
   "chksum_sha256": null,
   "format": 1
  }
 ],
 "format": 1
}